{
  "app": [
    {
      "definition": {
        "appV2": {
          "type": "front-end",
          "id": "c85fb6fb-700e-4f57-a592-d29d51c1d4fa",
          "name": "323",
          "slug": "c85fb6fb-700e-4f57-a592-d29d51c1d4fa",
          "isPublic": null,
          "isMaintenanceOn": false,
          "icon": "draghandle",
          "organizationId": "21c4df3f-de85-4e92-bc43-74aab8dc662b",
          "currentVersionId": null,
          "userId": "5dd9f34d-15f2-4ea1-afc7-c85431ef1172",
          "workflowApiToken": null,
          "workflowEnabled": false,
          "createdAt": "2025-02-04T05:57:40.558Z",
          "creationMode": "DEFAULT",
          "updatedAt": "2025-02-04T05:57:40.514Z",
          "editingVersion": {
            "id": "5a387534-5c72-44a4-b7ec-141091f7219d",
            "name": "v1",
            "definition": null,
            "globalSettings": {
              "hideHeader": false,
              "appInMaintenance": false,
              "canvasMaxWidth": 100,
              "canvasMaxWidthType": "%",
              "canvasMaxHeight": 2400,
              "canvasBackgroundColor": "#edeff5",
              "backgroundFxQuery": "",
              "appMode": "auto"
            },
            "pageSettings": null,
            "showViewerNavigation": true,
            "homePageId": "795111bd-5a94-4d7b-bc25-667fcd7d2cd9",
            "appId": "c85fb6fb-700e-4f57-a592-d29d51c1d4fa",
            "currentEnvironmentId": "3e410423-3b8a-464d-8331-7e89742f888c",
            "promotedFrom": null,
            "createdAt": "2025-02-04T05:57:40.569Z",
            "updatedAt": "2025-02-04T05:57:40.514Z"
          },
          "components": [
            {
              "id": "35adda51-6d19-40d5-a4ef-03281384132a",
              "name": "table1",
              "type": "Table",
              "pageId": "795111bd-5a94-4d7b-bc25-667fcd7d2cd9",
              "parent": null,
              "properties": {
                "title": {
                  "value": "Table"
                },
                "visible": {
                  "value": "{{true}}"
                },
                "loadingState": {
                  "value": "{{false}}"
                },
                "data": {
                  "value": "{{ [ \n\t\t{ id: 1, name: 'Olivia Nguyen', email: 'olivia.nguyen@example.com', date: '15/05/2022', mobile_number: 9876543210, interest: ['Reading', 'Traveling','Photography'], photo: 'https://reqres.in/img/faces/7-image.jpg' }, \n\t\t{ id: 2, name: 'Liam Patel', email: 'liam.patel@example.com', date: '20/09/2021', mobile_number: 8765432109, interest: ['Cooking','Gardening','Hiking'], photo: 'https://reqres.in/img/faces/5-image.jpg' }, \n\t\t{ id: 3, name: 'Sophia Reyes', email: 'sophia.reyes@example.com', date: '01/01/2023', mobile_number: 7654321098, interest: ['Music','Dancing','Crafting'], photo: 'https://reqres.in/img/faces/3-image.jpg' }, \n\t\t{ id: 4, name: 'Jacob Hernandez', email: 'jacob.hernandez@example.com', date: '10/11/2022', mobile_number: 6543210987, interest: ['Reading', 'Traveling', 'Volunteering'], photo: 'https://reqres.in/img/faces/1-image.jpg' }, \n\t\t{ id: 5, name: 'William Sanchez', email: 'william.sanchez@example.com', date: '07/01/2021', mobile_number: 4321098765, interest: ['Music', 'Dancing', 'Hiking'], photo: 'https://reqres.in/img/faces/4-image.jpg' }, \n\t\t{ id: 6, name: 'Ethan Morales', email: 'ethan.morales@example.com', date: '05/11/2021', mobile_number: 2109876543, interest: ['Cooking', 'Traveling', 'Photography'], photo: 'https://reqres.in/img/faces/6-image.jpg' }, \n\t\t{ id: 7, name: 'Mia Tiana', email: 'mia.tiana@example.com', date: '21/11/2022', mobile_number: 1098705217, interest: ['Music', 'Gardening', 'Hiking'], photo: 'https://reqres.in/img/faces/2-image.jpg' }, \n\t\t{ id: 8, name: 'Lucas Ramirez', email: 'lucas.ramirez@example.com', date: '31/03/2023', mobile_number: 9876543210, interest: ['Reading', 'Dancing', 'Crafting'], photo: 'https://reqres.in/img/faces/9-image.jpg' }, \n\t\t{ id: 9, name: 'Alexander Vela', email: 'alexander.vela@example.com', date: '07/09/2022', mobile_number: 7654321098, interest: ['Music','Gardening','Photography'], photo: 'https://reqres.in/img/faces/8-image.jpg' }, \n\t\t{ id: 10, name: 'Michael Reyes', email: 'michael.reyes@example.com', date: '25/12/2021', mobile_number: 5432109876, interest: ['Cooking','Crafting','Volunteering'], photo: 'https://reqres.in/img/faces/10-image.jpg' } \n] }}"
                },
                "useDynamicColumn": {
                  "value": "{{false}}"
                },
                "columnData": {
                  "value": "{{[{name: 'email', key: 'email', id: '1'}, {name: 'Full name', key: 'name', id: '2', isEditable: true}]}}"
                },
                "rowsPerPage": {
                  "value": "{{10}}"
                },
                "serverSidePagination": {
                  "value": "{{false}}"
                },
                "enableNextButton": {
                  "value": "{{true}}"
                },
                "enablePrevButton": {
                  "value": "{{true}}"
                },
                "totalRecords": {
                  "value": "{{10}}"
                },
                "enablePagination": {
                  "value": "{{true}}"
                },
                "serverSideSort": {
                  "value": "{{false}}"
                },
                "serverSideFilter": {
                  "value": "{{false}}"
                },
                "displaySearchBox": {
                  "value": "{{true}}"
                },
                "showDownloadButton": {
                  "value": "{{true}}"
                },
                "showFilterButton": {
                  "value": "{{true}}"
                },
                "autogenerateColumns": {
                  "value": true,
                  "generateNestedColumns": true
                },
                "isAllColumnsEditable": {
                  "value": "{{false}}"
                },
                "columns": {
                  "value": [
                    {
                      "name": "id",
                      "id": "e3ecbf7fa52c4d7210a93edb8f43776267a489bad52bd108be9588f790126737",
                      "autogenerated": true,
                      "fxActiveFields": [],
                      "columnSize": 30,
                      "columnType": "string"
                    },
                    {
                      "name": "photo",
                      "key": "photo",
                      "id": "f23b7d134b2e490ea41e3bb8eeb8c8e37472af243bf6b70d5af294482097e3a2",
                      "autogenerated": true,
                      "fxActiveFields": [],
                      "columnType": "image",
                      "objectFit": "contain",
                      "borderRadius": "100",
                      "columnSize": 70
                    },
                    {
                      "name": "name",
                      "id": "5d2a3744a006388aadd012fcc15cc0dbcb5f9130e0fbb64c558561c97118754a",
                      "autogenerated": true,
                      "fxActiveFields": [],
                      "columnSize": 130,
                      "columnType": "string"
                    },
                    {
                      "name": "email",
                      "id": "afc9a5091750a1bd4760e38760de3b4be11a43452ae8ae07ce2eebc569fe9a7f",
                      "autogenerated": true,
                      "fxActiveFields": [],
                      "columnSize": 230,
                      "columnType": "string"
                    },
                    {
                      "name": "date",
                      "id": "27b75c8af9d34d1eaa1f9bb7f8f9f7b0abf1823e799748c8bb57e74f53b2c1dc",
                      "autogenerated": true,
                      "fxActiveFields": [],
                      "columnType": "datepicker",
                      "isTimeChecked": false,
                      "dateFormat": "DD/MM/YYYY",
                      "parseDateFormat": "DD/MM/YYYY",
                      "isDateSelectionEnabled": true,
                      "columnSize": 130
                    },
                    {
                      "name": "mobile_number",
                      "id": "9c2e3c40572a4aefb8e179ee39a0e1ac9dc2b2e6634be56e1c05be13c3d1de56",
                      "autogenerated": true,
                      "fxActiveFields": [],
                      "columnType": "number",
                      "columnSize": 140
                    },
                    {
                      "name": "interest",
                      "key": "interest",
                      "id": "f23b7d134b2e490ea41e3bb8eeb8c8e37472af243bf6b70d5af294482097e3a1",
                      "autogenerated": true,
                      "fxActiveFields": [],
                      "columnType": "newMultiSelect",
                      "columnSize": 300,
                      "options": [
                        {
                          "label": "Reading",
                          "value": "Reading"
                        },
                        {
                          "label": "Traveling",
                          "value": "Traveling"
                        },
                        {
                          "label": "Photography",
                          "value": "Photography"
                        },
                        {
                          "label": "Music",
                          "value": "Music"
                        },
                        {
                          "label": "Cooking",
                          "value": "Cooking"
                        },
                        {
                          "label": "Crafting",
                          "value": "Crafting"
                        },
                        {
                          "label": "Voluntering",
                          "value": "Voluntering"
                        },
                        {
                          "label": "Garndening",
                          "value": "Garndening"
                        },
                        {
                          "label": "Dancing",
                          "value": "Dancing"
                        },
                        {
                          "label": "Hiking",
                          "value": "Hiking"
                        }
                      ]
                    }
                  ]
                },
                "showBulkUpdateActions": {
                  "value": "{{true}}"
                },
                "showBulkSelector": {
                  "value": "{{false}}"
                },
                "highlightSelectedRow": {
                  "value": "{{false}}"
                },
                "columnSizes": {
                  "value": "{{({})}}"
                },
                "actions": {
                  "value": []
                },
                "enabledSort": {
                  "value": "{{true}}"
                },
                "hideColumnSelectorButton": {
                  "value": "{{false}}"
                },
                "defaultSelectedRow": {
                  "value": "{{{\"id\":1}}}"
                },
                "showAddNewRowButton": {
                  "value": "{{true}}"
                },
                "allowSelection": {
                  "value": "{{true}}"
                },
                "visibility": {
                  "value": "{{true}}"
                },
                "disabledState": {
                  "value": "{{false}}"
                }
              },
              "general": {},
              "styles": {
                "textColor": {
                  "value": "#000"
                },
                "columnHeaderWrap": {
                  "value": "fixed"
                },
                "actionButtonRadius": {
                  "value": "0"
                },
                "cellSize": {
                  "value": "regular"
                },
                "borderRadius": {
                  "value": "8"
                },
                "tableType": {
                  "value": "table-classic"
                },
                "maxRowHeight": {
                  "value": "auto"
                },
                "maxRowHeightValue": {
                  "value": "{{0}}"
                },
                "contentWrap": {
                  "value": "{{true}}"
                },
                "boxShadow": {
                  "value": "0px 0px 0px 0px #00000090"
                },
                "padding": {
                  "value": "default"
                }
              },
              "generalStyles": {
                "boxShadow": {
                  "value": "0px 0px 0px 0px #00000040"
                }
              },
              "displayPreferences": {
                "showOnDesktop": {
                  "value": "{{true}}"
                },
                "showOnMobile": {
                  "value": "{{false}}"
                }
              },
              "validation": {},
              "createdAt": "2025-02-04T05:57:46.363Z",
              "updatedAt": "2025-02-04T05:57:46.572Z",
              "layouts": [
                {
                  "id": "69eb1142-b9bd-45bc-9bb4-d07f842bc432",
                  "type": "mobile",
                  "top": 40,
                  "left": 4,
                  "width": 35,
                  "height": 456,
                  "componentId": "35adda51-6d19-40d5-a4ef-03281384132a",
                  "dimensionUnit": "count",
                  "updatedAt": "2025-02-04T05:57:46.363Z"
                },
                {
                  "id": "6ffc93e4-40cd-44f8-8e25-fad86fc79342",
                  "type": "desktop",
                  "top": 240,
                  "left": 1,
                  "width": 35,
                  "height": 456,
                  "componentId": "35adda51-6d19-40d5-a4ef-03281384132a",
                  "dimensionUnit": "count",
                  "updatedAt": "2025-02-04T05:57:55.410Z"
                }
              ]
            },
            {
              "id": "4e844197-f79f-4bf0-ae52-fb64dfd8e8a8",
              "name": "button1",
              "type": "Button",
              "pageId": "795111bd-5a94-4d7b-bc25-667fcd7d2cd9",
              "parent": null,
              "properties": {
                "text": {
                  "value": "Button"
                },
                "visibility": {
                  "value": "{{true}}"
                },
                "disabledState": {
                  "value": "{{false}}"
                },
                "loadingState": {
                  "value": "{{false}}"
                },
                "tooltip": {
                  "value": ""
                }
              },
              "general": {},
              "styles": {
                "textColor": {
                  "value": "#FFFFFF"
                },
                "borderColor": {
                  "value": "#4368E3"
                },
                "loaderColor": {
                  "value": "#FFFFFF"
                },
                "borderRadius": {
                  "value": "{{6}}"
                },
                "backgroundColor": {
                  "value": "#4368E3"
                },
                "iconColor": {
                  "value": "#FFFFFF"
                },
                "direction": {
                  "value": "left"
                },
                "padding": {
                  "value": "default"
                },
                "boxShadow": {
                  "value": "0px 0px 0px 0px #00000090"
                },
                "icon": {
                  "value": "IconAlignBoxBottomLeft"
                },
                "iconVisibility": {
                  "value": false
                },
                "type": {
                  "value": "primary"
                }
              },
              "generalStyles": {
                "boxShadow": {
                  "value": "0px 0px 0px 0px #00000040"
                }
              },
              "displayPreferences": {
                "showOnDesktop": {
                  "value": "{{true}}"
                },
                "showOnMobile": {
                  "value": "{{false}}"
                }
              },
              "validation": {},
              "createdAt": "2025-02-04T05:57:58.400Z",
              "updatedAt": "2025-02-04T05:57:58.400Z",
              "layouts": [
                {
                  "id": "19ecbaf9-ff6c-4f5a-8333-113eefeb2048",
                  "type": "desktop",
                  "top": 120,
                  "left": 23,
                  "width": 4,
                  "height": 40,
                  "componentId": "4e844197-f79f-4bf0-ae52-fb64dfd8e8a8",
                  "dimensionUnit": "count",
                  "updatedAt": "2025-02-04T05:57:58.400Z"
                },
                {
                  "id": "24d9b06e-5e57-4838-a032-ec1bfee9d09c",
                  "type": "mobile",
                  "top": 120,
                  "left": 23,
                  "width": 4,
                  "height": 40,
                  "componentId": "4e844197-f79f-4bf0-ae52-fb64dfd8e8a8",
                  "dimensionUnit": "count",
                  "updatedAt": "2025-02-04T05:57:58.400Z"
                }
              ]
            }
          ],
          "pages": [
            {
              "id": "795111bd-5a94-4d7b-bc25-667fcd7d2cd9",
              "name": "Home",
              "handle": "home",
              "index": 1,
              "disabled": null,
              "hidden": null,
              "icon": null,
              "createdAt": "2025-02-04T05:57:40.514Z",
              "updatedAt": "2025-02-04T05:57:41.465Z",
              "autoComputeLayout": true,
              "appVersionId": "5a387534-5c72-44a4-b7ec-141091f7219d",
              "pageGroupIndex": 1,
              "pageGroupId": null,
              "isPageGroup": false
            }
          ],
          "events": [],
          "dataQueries": [],
          "dataSources": [],
          "appVersions": [
            {
              "id": "5a387534-5c72-44a4-b7ec-141091f7219d",
              "name": "v1",
              "definition": null,
              "globalSettings": {
                "hideHeader": false,
                "appInMaintenance": false,
                "canvasMaxWidth": 100,
                "canvasMaxWidthType": "%",
                "canvasMaxHeight": 2400,
                "canvasBackgroundColor": "#edeff5",
                "backgroundFxQuery": "",
                "appMode": "auto"
              },
              "pageSettings": null,
              "showViewerNavigation": true,
              "homePageId": "795111bd-5a94-4d7b-bc25-667fcd7d2cd9",
              "appId": "c85fb6fb-700e-4f57-a592-d29d51c1d4fa",
              "currentEnvironmentId": "3e410423-3b8a-464d-8331-7e89742f888c",
              "promotedFrom": null,
              "createdAt": "2025-02-04T05:57:40.569Z",
              "updatedAt": "2025-02-04T05:57:40.514Z"
            }
          ],
          "appEnvironments": [
            {
              "id": "3e410423-3b8a-464d-8331-7e89742f888c",
              "organizationId": "21c4df3f-de85-4e92-bc43-74aab8dc662b",
              "name": "development",
              "isDefault": false,
              "priority": 1,
              "enabled": true,
              "createdAt": "2025-02-04T03:20:03.875Z",
              "updatedAt": "2025-02-04T03:20:03.875Z"
            },
            {
              "id": "599cd209-8cb9-4a72-afa0-6dd5b9dec103",
              "organizationId": "21c4df3f-de85-4e92-bc43-74aab8dc662b",
              "name": "staging",
              "isDefault": false,
              "priority": 2,
              "enabled": true,
              "createdAt": "2025-02-04T03:20:03.875Z",
              "updatedAt": "2025-02-04T03:20:03.875Z"
            },
            {
              "id": "b599f50e-b742-4f4c-9b31-398dde059789",
              "organizationId": "21c4df3f-de85-4e92-bc43-74aab8dc662b",
              "name": "production",
              "isDefault": true,
              "priority": 3,
              "enabled": true,
              "createdAt": "2025-02-04T03:20:03.875Z",
              "updatedAt": "2025-02-04T03:20:03.875Z"
            }
          ],
          "dataSourceOptions": [],
          "schemaDetails": {
            "multiPages": true,
            "multiEnv": true,
            "globalDataSources": true
          }
        }
      }
    }
  ],
  "tooljet_version": "3.0.33-ee-lts"
}